infi.traceback-0.3.17-py2.7-nspkg.pth
infi/traceback/__init__.py
infi/traceback/__main__.py
infi/traceback/__version__.py
infi/traceback/tests.py
infi.traceback-0.3.17.dist-info/LICENSE
infi.traceback-0.3.17.dist-info/METADATA
infi.traceback-0.3.17.dist-info/WHEEL
infi.traceback-0.3.17.dist-info/entry_points.txt
infi.traceback-0.3.17.dist-info/namespace_packages.txt
infi.traceback-0.3.17.dist-info/top_level.txt
infi.traceback-0.3.17.dist-info/RECORD
