Metadata-Version: 2.1
Name: infi.traceback
Version: 0.3.17
Summary: better tracebacks
Home-page: https://github.com/Infinidat/infi.traceback
Author: Arnon Yaari
Author-email: arnony@infinidat.com
License: BSD
Platform: UNKNOWN
Classifier: Intended Audience :: Developers
Classifier: Intended Audience :: System Administrators
Classifier: License :: OSI Approved :: BSD License
Classifier: Operating System :: OS Independent
Classifier: Programming Language :: Python
Classifier: Programming Language :: Python :: 2
Classifier: Programming Language :: Python :: 3
Classifier: Topic :: Software Development :: Libraries :: Python Modules
Requires-Dist: infi.exceptools
Requires-Dist: infi.pyutils
Requires-Dist: nose
Requires-Dist: setuptools
